social_2fa/__init__.py
social_2fa/apps.py
social_2fa/social_pipeline.py
social_2fa/urls.py
social_2fa/views.py
social_2fa/tests/.test_views.py.swp
social_2fa/tests/__init__.py
social_2fa/tests/test_pipeline.py
social_2fa/tests/test_views.py
dj_two_factor_social_auth-1.0.1.dist-info/AUTHORS.rst
dj_two_factor_social_auth-1.0.1.dist-info/LICENSE
dj_two_factor_social_auth-1.0.1.dist-info/METADATA
dj_two_factor_social_auth-1.0.1.dist-info/WHEEL
dj_two_factor_social_auth-1.0.1.dist-info/top_level.txt
dj_two_factor_social_auth-1.0.1.dist-info/RECORD
