Metadata-Version: 2.1
Name: dj-two-factor-social-auth
Version: 1.0.1
Summary: App connecting django-two-factor-auth and django-social-auth. If user authenticates through social auth, he will be enforced to go through 2FA (if he has it enabled).
Home-page: https://github.com/PetrDlouhy/dj-2fa-social-auth
Author: Petr Dlouhý
Author-email: petr.dlouhy@email.cz
License: BSD
Keywords: dj-2fa-social-auth
Classifier: Development Status :: 5 - Production/Stable
Classifier: Framework :: Django :: 3.2
Classifier: Framework :: Django :: 4.0
Classifier: Framework :: Django :: 4.1
Classifier: Framework :: Django :: 4.2
Classifier: Framework :: Django :: 5.0
Classifier: Framework :: Django :: 5.1
Classifier: Framework :: Django :: 5.2
Classifier: Intended Audience :: Developers
Classifier: License :: OSI Approved :: BSD License
Classifier: Natural Language :: English
Classifier: Programming Language :: Python :: 3
Classifier: Programming Language :: Python :: 3.8
Classifier: Programming Language :: Python :: 3.9
Classifier: Programming Language :: Python :: 3.10
Classifier: Programming Language :: Python :: 3.11
Classifier: Programming Language :: Python :: 3.12
Classifier: Programming Language :: Python :: 3.13
License-File: LICENSE
License-File: AUTHORS.rst
Requires-Dist: django-model-utils (>=2.0)
Requires-Dist: django-two-factor-auth
Requires-Dist: social-auth-app-django
